buba/__init__.py
buba-0.0.1.dist-info/LICENSE
buba-0.0.1.dist-info/METADATA
buba-0.0.1.dist-info/WHEEL
buba-0.0.1.dist-info/top_level.txt
buba-0.0.1.dist-info/RECORD
