Metadata-Version: 2.1
Name: buba
Version: 0.0.1
Summary: Multi-environment yaml settings following 12 Factor App methodology.
Home-page: https://github.com/code-impactor/buba
Author: Andrei Roskach
Author-email: code.impactor@gmail.com
License: MIT
Download-URL: https://github.com/code-impactor/buba/releases/tag/0.0.1
Keywords: multi-environment,yaml,settings,config,12 Factor,python,nested
Platform: Any
Classifier: Intended Audience :: Developers
Classifier: Programming Language :: Python
Classifier: Natural Language :: English
Classifier: License :: OSI Approved :: MIT License
Classifier: Operating System :: OS Independent
Classifier: Topic :: Software Development :: Libraries
Requires-Python: >=2.7
Requires-Dist: PyYAML (>=5.3)
